asyncio_connection_pool/__init__.py
asyncio_connection_pool/py.typed
asyncio_connection_pool/contrib/__init__.py
asyncio_connection_pool/contrib/datadog.py
asyncio_connection_pool-1.1.1.dist-info/METADATA
asyncio_connection_pool-1.1.1.dist-info/WHEEL
asyncio_connection_pool-1.1.1.dist-info/licenses/LICENSE
asyncio_connection_pool-1.1.1.dist-info/RECORD
