Metadata-Version: 2.4
Name: asyncio-connection-pool
Version: 1.1.1
Summary: A high-throughput, optionally-burstable pool free of explicit locking
Project-URL: Homepage, https://github.com/fellowapp/asyncio-connection-pool
Project-URL: Repository, https://github.com/fellowapp/asyncio-connection-pool
Project-URL: Changelog, https://github.com/fellowapp/asyncio-connection-pool/releases
Author-email: Patrick Gingras <775.pg.12@gmail.com>
License: BSD-3-Clause
License-File: LICENSE
Classifier: Development Status :: 5 - Production/Stable
Classifier: Intended Audience :: Developers
Classifier: License :: OSI Approved :: BSD License
Classifier: Operating System :: OS Independent
Classifier: Programming Language :: Python
Classifier: Programming Language :: Python :: 3 :: Only
Classifier: Programming Language :: Python :: 3.10
Classifier: Programming Language :: Python :: 3.11
Classifier: Programming Language :: Python :: 3.12
Classifier: Programming Language :: Python :: 3.13
Classifier: Topic :: Software Development :: Libraries :: Python Modules
Classifier: Typing :: Typed
Requires-Python: >=3.10
Provides-Extra: datadog
Requires-Dist: datadog; extra == 'datadog'
Requires-Dist: ddtrace; extra == 'datadog'
